Physcraper-1.0.0.data/scripts/find_trees.py
Physcraper-1.0.0.data/scripts/multi_loci.py
Physcraper-1.0.0.data/scripts/physcraper_run.py
Physcraper-1.0.0.data/scripts/tree_comparison.py
physcraper/AWSWWW.py
physcraper/__init__.py
physcraper/aligntreetax.py
physcraper/configobj.py
physcraper/helpers.py
physcraper/ids.py
physcraper/ncbi_data_parser.py
physcraper/opentree_helpers.py
physcraper/scrape.py
physcraper/treetaxon.py
Physcraper-1.0.0.dist-info/LICENSE
Physcraper-1.0.0.dist-info/METADATA
Physcraper-1.0.0.dist-info/WHEEL
Physcraper-1.0.0.dist-info/pbr.json
Physcraper-1.0.0.dist-info/top_level.txt
Physcraper-1.0.0.dist-info/RECORD
