Metadata-Version: 2.1
Name: Physcraper
Version: 1.0.0
Summary: Physcraper
Home-page: https://github.com/McTavishLab/physcraper
Author: Emily Jane McTavish
Author-email: ejmctavish@gmail.com
License: UNKNOWN
Platform: UNKNOWN
License-File: LICENSE
Requires-Dist: argparse
Requires-Dist: biopython (==1.76)
Requires-Dist: configparser
Requires-Dist: DendroPy
Requires-Dist: DateTime
Requires-Dist: opentree
Requires-Dist: pandas
Requires-Dist: requests
Requires-Dist: sh
Requires-Dist: urllib3 (>=1.23)
Requires-Dist: numpy
Requires-Dist: wget
